[
  {
    "项目名称": "蒙能内蒙古呼伦贝尔市满洲里绿色供电",
    "现场经理": "韩忠伟",
    "机组": "/",
    "问题": "独立变桨技改，导致通讯中断",
    "向现场提出时间": "2026年4月30日",
    "是否闭环": "已闭环",
    "闭环情况（当前状态+时间节点）": "5月6日：独立变桨技改未完成\n5/15独立变桨技改未完成，有配件仍未到位\n5/29：已全部恢复",
    "动态N比例（全场）/%": "41.8",
    "低净空比例（全场）/%": "2.4"
  },
  {
    "项目名称": "蒙能内蒙古阿拉善右旗",
    "现场经理": "王志刚",
    "机组": "MN030",
    "问题": "雷达故障",
    "向现场提出时间": "2026年4月30日",
    "是否闭环": "已闭环",
    "闭环情况（当前状态+时间节点）": "5月6日：近期大风，业主保发电量，预计明后天处理\n5/15已处理",
    "动态N比例（全场）/%": "2.2",
    "低净空比例（全场）/%": "0.5"
  },
  {
    "项目名称": "",
    "现场经理": "",
    "机组": "MN2",
    "问题": "光束3脏污",
    "向现场提出时间": "",
    "是否闭环": "已闭环",
    "闭环情况（当前状态+时间节点）": "",
    "动态N比例（全场）/%": "",
    "低净空比例（全场）/%": ""
  },
  {
    "项目名称": "",
    "现场经理": "",
    "机组": "MN34",
    "问题": "光束3脏污",
    "向现场提出时间": "",
    "是否闭环": "已闭环",
    "闭环情况（当前状态+时间节点）": "",
    "动态N比例（全场）/%": "",
    "低净空比例（全场）/%": ""
  },
  {
    "项目名称": "",
    "现场经理": "",
    "机组": "MN39",
    "问题": "通讯中断",
    "向现场提出时间": "",
    "是否闭环": "已闭环",
    "闭环情况（当前状态+时间节点）": "",
    "动态N比例（全场）/%": "",
    "低净空比例（全场）/%": ""
  },
  {
    "项目名称": "粤水电新疆布尔津三期",
    "现场经理": "林海",
    "机组": "#40",
    "问题": "雷达脏污",
    "向现场提出时间": "2026年4月30日",
    "是否闭环": "已闭环",
    "闭环情况（当前状态+时间节点）": "5月6日：已处理",
    "动态N比例（全场）/%": "2.7",
    "低净空比例（全场）/%": "0"
  },
  {
    "项目名称": "",
    "现场经理": "",
    "机组": "#41",
    "问题": "光束3脏污",
    "向现场提出时间": "",
    "是否闭环": "已闭环",
    "闭环情况（当前状态+时间节点）": "5月6日：已处理",
    "动态N比例（全场）/%": "",
    "低净空比例（全场）/%": ""
  },
  {
    "项目名称": "",
    "现场经理": "",
    "机组": "#42",
    "问题": "光束1脏污",
    "向现场提出时间": "",
    "是否闭环": "已闭环",
    "闭环情况（当前状态+时间节点）": "5月6日：已处理",
    "动态N比例（全场）/%": "",
    "低净空比例（全场）/%": ""
  },
  {
    "项目名称": "华电新疆天山北麓基地标段五",
    "现场经理": "徐国强",
    "机组": "/",
    "问题": "未升级净空程序版本",
    "向现场提出时间": "2026年5月6日",
    "是否闭环": "未闭环",
    "闭环情况（当前状态+时间节点）": "5/15现场刚收到第二版程序，预计月底完成全部机组升级",
    "动态N比例（全场）/%": "28.5",
    "低净空比例（全场）/%": "0"
  },
  {
    "项目名称": "",
    "现场经理": "",
    "机组": "H01",
    "问题": "通讯中断",
    "向现场提出时间": "2026年5月25日",
    "是否闭环": "未闭环",
    "闭环情况（当前状态+时间节点）": "",
    "动态N比例（全场）/%": "",
    "低净空比例（全场）/%": ""
  },
  {
    "项目名称": "",
    "现场经理": "",
    "机组": "H09",
    "问题": "光束3脏污",
    "向现场提出时间": "2026年5月25日",
    "是否闭环": "未闭环",
    "闭环情况（当前状态+时间节点）": "",
    "动态N比例（全场）/%": "",
    "低净空比例（全场）/%": ""
  },
  {
    "项目名称": "",
    "现场经理": "",
    "机组": "H18",
    "问题": "通讯中断",
    "向现场提出时间": "2026年5月25日",
    "是否闭环": "未闭环",
    "闭环情况（当前状态+时间节点）": "",
    "动态N比例（全场）/%": "",
    "低净空比例（全场）/%": ""
  },
  {
    "项目名称": "",
    "现场经理": "",
    "机组": "H28",
    "问题": "通讯中断",
    "向现场提出时间": "2026年5月25日",
    "是否闭环": "未闭环",
    "闭环情况（当前状态+时间节点）": "",
    "动态N比例（全场）/%": "",
    "低净空比例（全场）/%": ""
  },
  {
    "项目名称": "",
    "现场经理": "",
    "机组": "H41",
    "问题": "通讯中断",
    "向现场提出时间": "2026年5月25日",
    "是否闭环": "未闭环",
    "闭环情况（当前状态+时间节点）": "",
    "动态N比例（全场）/%": "",
    "低净空比例（全场）/%": ""
  },
  {
    "项目名称": "",
    "现场经理": "",
    "机组": "H42",
    "问题": "雷达脏污",
    "向现场提出时间": "2026年5月25日",
    "是否闭环": "未闭环",
    "闭环情况（当前状态+时间节点）": "",
    "动态N比例（全场）/%": "",
    "低净空比例（全场）/%": ""
  },
  {
    "项目名称": "",
    "现场经理": "",
    "机组": "H48",
    "问题": "雷达脏污",
    "向现场提出时间": "2026年5月25日",
    "是否闭环": "未闭环",
    "闭环情况（当前状态+时间节点）": "",
    "动态N比例（全场）/%": "",
    "低净空比例（全场）/%": ""
  },
  {
    "项目名称": "",
    "现场经理": "",
    "机组": "H55",
    "问题": "通讯中断",
    "向现场提出时间": "2026年5月25日",
    "是否闭环": "未闭环",
    "闭环情况（当前状态+时间节点）": "5/29：已调试",
    "动态N比例（全场）/%": "",
    "低净空比例（全场）/%": ""
  },
  {
    "项目名称": "",
    "现场经理": "",
    "机组": "H58",
    "问题": "雷达脏污",
    "向现场提出时间": "2026年5月25日",
    "是否闭环": "未闭环",
    "闭环情况（当前状态+时间节点）": "",
    "动态N比例（全场）/%": "",
    "低净空比例（全场）/%": ""
  },
  {
    "项目名称": "华润天津九园",
    "现场经理": "宋磊",
    "机组": "#3G",
    "问题": "视频异常",
    "向现场提出时间": "2026年5月6日",
    "是否闭环": "已闭环",
    "闭环情况（当前状态+时间节点）": "5/14安排厂家排查处理\n5/19厂家到场开始处理\n5/29：通讯已恢复",
    "动态N比例（全场）/%": "5.3",
    "低净空比例（全场）/%": "0"
  },
  {
    "项目名称": "石家庄能投河北石家庄深泽",
    "现场经理": "田伟",
    "机组": "#9",
    "问题": "光束3脏污",
    "向现场提出时间": "2026年5月6日",
    "是否闭环": "已闭环",
    "闭环情况（当前状态+时间节点）": "4/28已处理",
    "动态N比例（全场）/%": "7.4",
    "低净空比例（全场）/%": "0"
  },
  {
    "项目名称": "",
    "现场经理": "",
    "机组": "#10",
    "问题": "光束1脏污",
    "向现场提出时间": "2026年5月6日",
    "是否闭环": "已闭环",
    "闭环情况（当前状态+时间节点）": "5/5已处理",
    "动态N比例（全场）/%": "",
    "低净空比例（全场）/%": ""
  },
  {
    "项目名称": "",
    "现场经理": "",
    "机组": "#12",
    "问题": "光束1脏污",
    "向现场提出时间": "2026年5月6日",
    "是否闭环": "已闭环",
    "闭环情况（当前状态+时间节点）": "5/1已处理",
    "动态N比例（全场）/%": "",
    "低净空比例（全场）/%": ""
  },
  {
    "项目名称": "",
    "现场经理": "",
    "机组": "#14",
    "问题": "光束1脏污",
    "向现场提出时间": "2026年5月6日",
    "是否闭环": "已闭环",
    "闭环情况（当前状态+时间节点）": "5/1已处理",
    "动态N比例（全场）/%": "",
    "低净空比例（全场）/%": ""
  },
  {
    "项目名称": "Marubeni沙特第四轮WAS",
    "现场经理": "王盼锋",
    "机组": "A05",
    "问题": "程序未升级",
    "向现场提出时间": "2026年5月22日",
    "是否闭环": "已闭环",
    "闭环情况（当前状态+时间节点）": "5/29：已升级",
    "动态N比例（全场）/%": "7.4",
    "低净空比例（全场）/%": "0"
  },
  {
    "项目名称": "",
    "现场经理": "",
    "机组": "A06",
    "问题": "程序未升级",
    "向现场提出时间": "2026年5月22日",
    "是否闭环": "已闭环",
    "闭环情况（当前状态+时间节点）": "5/29：已升级",
    "动态N比例（全场）/%": "",
    "低净空比例（全场）/%": ""
  },
  {
    "项目名称": "",
    "现场经理": "",
    "机组": "A07",
    "问题": "程序未升级",
    "向现场提出时间": "2026年5月22日",
    "是否闭环": "已闭环",
    "闭环情况（当前状态+时间节点）": "5/29：已升级",
    "动态N比例（全场）/%": "",
    "低净空比例（全场）/%": ""
  },
  {
    "项目名称": "",
    "现场经理": "",
    "机组": "A08",
    "问题": "程序未升级",
    "向现场提出时间": "2026年5月22日",
    "是否闭环": "已闭环",
    "闭环情况（当前状态+时间节点）": "5/29：已升级",
    "动态N比例（全场）/%": "",
    "低净空比例（全场）/%": ""
  },
  {
    "项目名称": "",
    "现场经理": "",
    "机组": "A12",
    "问题": "程序未升级",
    "向现场提出时间": "2026年5月22日",
    "是否闭环": "已闭环",
    "闭环情况（当前状态+时间节点）": "5/29：已升级",
    "动态N比例（全场）/%": "",
    "低净空比例（全场）/%": ""
  },
  {
    "项目名称": "",
    "现场经理": "",
    "机组": "A13",
    "问题": "程序未升级",
    "向现场提出时间": "2026年5月22日",
    "是否闭环": "已闭环",
    "闭环情况（当前状态+时间节点）": "5/29：已升级",
    "动态N比例（全场）/%": "",
    "低净空比例（全场）/%": ""
  },
  {
    "项目名称": "Marubeni沙特第四轮AGA",
    "现场经理": "冯雷康",
    "机组": "",
    "问题": "",
    "向现场提出时间": "",
    "是否闭环": "",
    "闭环情况（当前状态+时间节点）": "",
    "动态N比例（全场）/%": "1.1",
    "低净空比例（全场）/%": "0"
  },
  {
    "项目名称": "Marubeni沙特第四轮YAN",
    "现场经理": "田武斌",
    "机组": "",
    "问题": "",
    "向现场提出时间": "",
    "是否闭环": "",
    "闭环情况（当前状态+时间节点）": "5/29：项目未吊装",
    "动态N比例（全场）/%": "",
    "低净空比例（全场）/%": ""
  }
]